DynamicDoc/__init__.py
DynamicDoc/dynamicdoc.py
DynamicDoc/verificadores.py
DynamicDoc-1.0.0.dist-info/LICENSE.txt
DynamicDoc-1.0.0.dist-info/METADATA
DynamicDoc-1.0.0.dist-info/WHEEL
DynamicDoc-1.0.0.dist-info/top_level.txt
DynamicDoc-1.0.0.dist-info/RECORD
