Metadata-Version: 2.2
Name: DynamicDoc
Version: 1.0.0
Summary: Uma biblioteca para manipulação dinâmica de documentos docx.
Home-page: https://github.com/SamuelSGSouza/Dynamic-Docs
Author: Samuel Santos
Author-email: samuels.g.desouza@gmail.com
Classifier: Programming Language :: Python :: 3
Classifier: License :: OSI Approved :: MIT License
Classifier: Operating System :: OS Independent
Requires-Python: >=3.6
License-File: LICENSE.txt
Requires-Dist: python-docx
Dynamic: author
Dynamic: author-email
Dynamic: classifier
Dynamic: description
Dynamic: description-content-type
Dynamic: home-page
Dynamic: requires-dist
Dynamic: requires-python
Dynamic: summary
